{
  "nist": [
    {
      "cpe": {
        "deprecated": false,
        "cpeName": "cpe:2.3:a:appeak:poker:2.4.5:*:*:*:*:android:*:*",
        "cpeNameId": "ECAFDA4F-4B96-46D8-89D7-7BA1A9832328",
        "lastModified": "2014-11-09T14:10:57.157",
        "created": "2014-09-09T18:55:12.477",
        "titles": [
          {
            "title": "Appeak Poker (aka com.appeak.poker) application for Android 2.4.5",
            "lang": "en"
          }
        ],
        "deprecatedBy": null
      }
    }
  ],
  "opencpe": [
    {
      "name": "cpe:2.3:a:appeak:poker:2.4.5:*:*:*:*:android:*:*",
      "title": "Appeak Poker (aka com.appeak.poker) application for Android 2.4.5",
      "deprecated": false,
      "deprecated_over": ""
    }
  ]
}
