{
  "nist": [
    {
      "cpe": {
        "deprecated": false,
        "cpeName": "cpe:2.3:h:intel:core_i5-10400t:-:*:*:*:*:*:*:*",
        "cpeNameId": "21F7A1D3-BD16-4EAD-9F27-9CA4346A71B1",
        "lastModified": "2021-04-30T14:53:17.223",
        "created": "2020-11-17T13:29:58.567",
        "titles": [
          {
            "title": "Intel Core i5-10400T",
            "lang": "en"
          }
        ],
        "deprecatedBy": null
      }
    }
  ],
  "opencpe": [
    {
      "name": "cpe:2.3:h:intel:core_i5-10400t:-:*:*:*:*:*:*:*",
      "title": "Intel Core i5-10400T",
      "deprecated": false,
      "deprecated_over": ""
    }
  ]
}
