{
  "nist": [
    {
      "cpe": {
        "deprecated": false,
        "cpeName": "cpe:2.3:h:intel:xeon_e5-2650_v3:-:*:*:*:*:*:*:*",
        "cpeNameId": "EAC564DC-4204-462F-B118-7F7A27FF7FF1",
        "lastModified": "2020-03-23T14:40:05.357",
        "created": "2020-03-23T14:40:05.357",
        "titles": [
          {
            "title": "Intel Xeon E5-2650 V3",
            "lang": "en"
          }
        ],
        "deprecatedBy": null
      }
    }
  ],
  "opencpe": [
    {
      "name": "cpe:2.3:h:intel:xeon_e5-2650_v3:-:*:*:*:*:*:*:*",
      "title": "Intel Xeon E5-2650 V3",
      "deprecated": false,
      "deprecated_over": ""
    }
  ]
}
