{
  "nist": [
    {
      "cpe": {
        "deprecated": false,
        "cpeName": "cpe:2.3:a:oracle:human_resources:11.5.10.2:*:*:*:*:*:*:*",
        "cpeNameId": "81DAF796-F6FD-4954-A597-D040C2C7C104",
        "lastModified": "2016-02-17T17:55:43.810",
        "created": "2016-02-17T17:55:43.810",
        "titles": [
          {
            "title": "Oracle Human Resources 11.5.10.2",
            "lang": "en"
          }
        ],
        "deprecatedBy": null
      }
    },
    {
      "cpe": {
        "deprecated": false,
        "cpeName": "cpe:2.3:a:oracle:human_resources:12.1.1:*:*:*:*:*:*:*",
        "cpeNameId": "C4936D0E-5951-4A1A-9E9E-A77741F3D790",
        "lastModified": "2019-05-22T17:32:00.667",
        "created": "2019-05-22T17:32:00.667",
        "titles": [
          {
            "title": "Oracle Human Resources 12.1.1",
            "lang": "en"
          }
        ],
        "deprecatedBy": null
      }
    },
    {
      "cpe": {
        "deprecated": false,
        "cpeName": "cpe:2.3:a:oracle:human_resources:12.1.2:*:*:*:*:*:*:*",
        "cpeNameId": "B9A6FFB9-626B-4F55-A1A8-75CFD574D89C",
        "lastModified": "2019-05-22T17:32:00.760",
        "created": "2019-05-22T17:32:00.760",
        "titles": [
          {
            "title": "Oracle Human Resources 12.1.2",
            "lang": "en"
          }
        ],
        "deprecatedBy": null
      }
    },
    {
      "cpe": {
        "deprecated": false,
        "cpeName": "cpe:2.3:a:oracle:human_resources:12.1.3:*:*:*:*:*:*:*",
        "cpeNameId": "A9F59763-62BD-4145-96F8-458A7DBDF7D3",
        "lastModified": "2019-05-22T17:32:00.853",
        "created": "2019-05-22T17:32:00.853",
        "titles": [
          {
            "title": "Oracle Human Resources 12.1.3",
            "lang": "en"
          }
        ],
        "deprecatedBy": null
      }
    },
    {
      "cpe": {
        "deprecated": false,
        "cpeName": "cpe:2.3:a:oracle:human_resources:12.2.3:*:*:*:*:*:*:*",
        "cpeNameId": "F55AB5C8-245E-4EE9-BB31-2A83A011A81F",
        "lastModified": "2019-05-22T17:32:00.930",
        "created": "2019-05-22T17:32:00.930",
        "titles": [
          {
            "title": "Oracle Human Resources 12.2.3",
            "lang": "en"
          }
        ],
        "deprecatedBy": null
      }
    },
    {
      "cpe": {
        "deprecated": false,
        "cpeName": "cpe:2.3:a:oracle:human_resources:12.2.4:*:*:*:*:*:*:*",
        "cpeNameId": "74A88894-C883-4E60-915C-7B4024E94DEE",
        "lastModified": "2019-05-22T17:32:01.027",
        "created": "2019-05-22T17:32:01.027",
        "titles": [
          {
            "title": "Oracle Human Resources 12.2.4",
            "lang": "en"
          }
        ],
        "deprecatedBy": null
      }
    },
    {
      "cpe": {
        "deprecated": false,
        "cpeName": "cpe:2.3:a:oracle:human_resources:12.2.5:*:*:*:*:*:*:*",
        "cpeNameId": "20BD7EBC-CF0E-4FAC-8DB8-F318A28CA964",
        "lastModified": "2019-05-22T17:32:01.117",
        "created": "2019-05-22T17:32:01.117",
        "titles": [
          {
            "title": "Oracle Human Resources 12.2.5",
            "lang": "en"
          }
        ],
        "deprecatedBy": null
      }
    },
    {
      "cpe": {
        "deprecated": false,
        "cpeName": "cpe:2.3:a:oracle:human_resources:12.2.6:*:*:*:*:*:*:*",
        "cpeNameId": "B9634CD9-4C4B-45A9-A64E-F4547CCEDEAE",
        "lastModified": "2019-05-22T17:32:01.213",
        "created": "2019-05-22T17:32:01.213",
        "titles": [
          {
            "title": "Oracle Human Resources 12.2.6",
            "lang": "en"
          }
        ],
        "deprecatedBy": null
      }
    },
    {
      "cpe": {
        "deprecated": false,
        "cpeName": "cpe:2.3:a:oracle:human_resources:12.2.7:*:*:*:*:*:*:*",
        "cpeNameId": "ADC8F27A-28FB-482E-8EA6-96C48BEA55FD",
        "lastModified": "2019-05-22T17:32:01.290",
        "created": "2019-05-22T17:32:01.290",
        "titles": [
          {
            "title": "Oracle Human Resources 12.2.7",
            "lang": "en"
          }
        ],
        "deprecatedBy": null
      }
    },
    {
      "cpe": {
        "deprecated": false,
        "cpeName": "cpe:2.3:a:oracle:human_resources:12.2.9:*:*:*:*:*:*:*",
        "cpeNameId": "7AB146B6-463A-4BDA-BC27-257AA9314CF8",
        "lastModified": "2020-01-17T18:57:21.100",
        "created": "2020-01-17T18:57:21.100",
        "titles": [
          {
            "title": "Oracle Human Resources 12.2.9",
            "lang": "en"
          }
        ],
        "deprecatedBy": null
      }
    }
  ],
  "opencpe": [
    {
      "name": "cpe:2.3:a:oracle:human_resources:11.5.10.2:*:*:*:*:*:*:*",
      "title": "Oracle Human Resources 11.5.10.2",
      "deprecated": false,
      "deprecated_over": ""
    },
    {
      "name": "cpe:2.3:a:oracle:human_resources:12.1.1:*:*:*:*:*:*:*",
      "title": "Oracle Human Resources 12.1.1",
      "deprecated": false,
      "deprecated_over": ""
    },
    {
      "name": "cpe:2.3:a:oracle:human_resources:12.1.2:*:*:*:*:*:*:*",
      "title": "Oracle Human Resources 12.1.2",
      "deprecated": false,
      "deprecated_over": ""
    },
    {
      "name": "cpe:2.3:a:oracle:human_resources:12.1.3:*:*:*:*:*:*:*",
      "title": "Oracle Human Resources 12.1.3",
      "deprecated": false,
      "deprecated_over": ""
    },
    {
      "name": "cpe:2.3:a:oracle:human_resources:12.2.3:*:*:*:*:*:*:*",
      "title": "Oracle Human Resources 12.2.3",
      "deprecated": false,
      "deprecated_over": ""
    },
    {
      "name": "cpe:2.3:a:oracle:human_resources:12.2.4:*:*:*:*:*:*:*",
      "title": "Oracle Human Resources 12.2.4",
      "deprecated": false,
      "deprecated_over": ""
    },
    {
      "name": "cpe:2.3:a:oracle:human_resources:12.2.5:*:*:*:*:*:*:*",
      "title": "Oracle Human Resources 12.2.5",
      "deprecated": false,
      "deprecated_over": ""
    },
    {
      "name": "cpe:2.3:a:oracle:human_resources:12.2.6:*:*:*:*:*:*:*",
      "title": "Oracle Human Resources 12.2.6",
      "deprecated": false,
      "deprecated_over": ""
    },
    {
      "name": "cpe:2.3:a:oracle:human_resources:12.2.7:*:*:*:*:*:*:*",
      "title": "Oracle Human Resources 12.2.7",
      "deprecated": false,
      "deprecated_over": ""
    },
    {
      "name": "cpe:2.3:a:oracle:human_resources:12.2.9:*:*:*:*:*:*:*",
      "title": "Oracle Human Resources 12.2.9",
      "deprecated": false,
      "deprecated_over": ""
    }
  ]
}
