{
  "nist": [
    {
      "cpe": {
        "deprecated": false,
        "cpeName": "cpe:2.3:a:makemytrip:makemytrip:7.2.4:*:*:*:*:android:*:*",
        "cpeNameId": "6828A504-94F5-4C8F-B29C-F811806F4F5B",
        "lastModified": "2019-08-07T18:04:56.047",
        "created": "2019-08-07T18:04:56.047",
        "titles": [
          {
            "title": "MakeMyTrip 7.2.4 for Android",
            "lang": "en"
          }
        ],
        "deprecatedBy": null
      }
    }
  ],
  "opencpe": [
    {
      "name": "cpe:2.3:a:makemytrip:makemytrip:7.2.4:*:*:*:*:android:*:*",
      "title": "MakeMyTrip 7.2.4 for Android",
      "deprecated": false,
      "deprecated_over": ""
    }
  ]
}
