{
  "nist": [
    {
      "cpe": {
        "deprecated": false,
        "cpeName": "cpe:2.3:h:cisco:telepresence_system_1300_65:-:*:*:*:*:*:*:*",
        "cpeNameId": "090063B3-DF1D-4AA2-A352-592075C77FDD",
        "lastModified": "2012-07-25T18:29:57.947",
        "created": "2012-07-12T14:37:53.077",
        "titles": [
          {
            "title": "Cisco TelePresence System 1300 65",
            "lang": "en"
          }
        ],
        "deprecatedBy": null
      }
    }
  ],
  "opencpe": [
    {
      "name": "cpe:2.3:h:cisco:telepresence_system_1300_65:-:*:*:*:*:*:*:*",
      "title": "Cisco TelePresence System 1300 65",
      "deprecated": false,
      "deprecated_over": ""
    }
  ]
}
