{
  "nist": [
    {
      "cpe": {
        "deprecated": false,
        "cpeName": "cpe:2.3:o:st:stm32l4_firmware:-:*:*:*:*:*:*:*",
        "cpeNameId": "F52BBDC3-F49D-427D-995C-4FE976E004D3",
        "lastModified": "2021-04-30T19:37:27.427",
        "created": "2019-09-16T17:31:19.323",
        "titles": [
          {
            "title": "STMicroelectronics STM32L4 Firmware",
            "lang": "en"
          }
        ],
        "deprecatedBy": null
      }
    }
  ],
  "opencpe": [
    {
      "name": "cpe:2.3:o:st:stm32l4_firmware:-:*:*:*:*:*:*:*",
      "title": "STMicroelectronics STM32L4 Firmware",
      "deprecated": false,
      "deprecated_over": ""
    }
  ]
}
