{
  "nist": [
    {
      "cpe": {
        "deprecated": false,
        "cpeName": "cpe:2.3:h:lexmark:xs748:-:*:*:*:*:*:*:*",
        "cpeNameId": "9F687CE6-86BD-443F-9A61-F71ED08913B6",
        "lastModified": "2019-12-28T15:45:02.633",
        "created": "2019-12-28T15:45:02.633",
        "titles": [
          {
            "title": "Lexmark XS748 -",
            "lang": "en"
          }
        ],
        "deprecatedBy": null
      }
    }
  ],
  "opencpe": [
    {
      "name": "cpe:2.3:h:lexmark:xs748:-:*:*:*:*:*:*:*",
      "title": "Lexmark XS748 -",
      "deprecated": false,
      "deprecated_over": ""
    }
  ]
}
