{
  "nist": [
    {
      "cpe": {
        "deprecated": false,
        "cpeName": "cpe:2.3:h:lenovo:330-17ast:-:*:*:*:*:*:*:*",
        "cpeNameId": "224BC1E9-158A-4052-947F-F7606F45B240",
        "lastModified": "2020-06-16T18:55:56.383",
        "created": "2020-06-16T18:55:56.383",
        "titles": [
          {
            "title": "Lenovo 330-17AST",
            "lang": "en"
          }
        ],
        "deprecatedBy": null
      }
    }
  ],
  "opencpe": [
    {
      "name": "cpe:2.3:h:lenovo:330-17ast:-:*:*:*:*:*:*:*",
      "title": "Lenovo 330-17AST",
      "deprecated": false,
      "deprecated_over": ""
    }
  ]
}
