{
  "nist": [
    {
      "cpe": {
        "deprecated": false,
        "cpeName": "cpe:2.3:a:kokoroe_members_card_project:kokoroe_members_card:13.6.1:*:*:*:*:line:*:*",
        "cpeNameId": "B3A0A573-6709-406E-BF6F-3C4D395996AB",
        "lastModified": "2024-08-01T14:26:06.633",
        "created": "2024-08-01T14:26:06.633",
        "titles": [
          {
            "title": "Kokoroe Members Card Project Kokoroe Members Card 13.6.1 for Line",
            "lang": "en"
          }
        ],
        "deprecatedBy": null
      }
    }
  ],
  "opencpe": [
    {
      "name": "cpe:2.3:a:kokoroe_members_card_project:kokoroe_members_card:13.6.1:*:*:*:*:line:*:*",
      "title": "Kokoroe Members Card Project Kokoroe Members Card 13.6.1 for Line",
      "deprecated": false,
      "deprecated_over": ""
    }
  ]
}
