{
  "nist": [
    {
      "cpe": {
        "deprecated": false,
        "cpeName": "cpe:2.3:h:phoenixcontact:axl_f_bk_pn:-:*:*:*:*:*:*:*",
        "cpeNameId": "FC65B3DF-F7A3-4A86-A131-31EB760068F2",
        "lastModified": "2020-03-04T14:38:52.687",
        "created": "2020-03-04T14:38:52.687",
        "titles": [
          {
            "title": "PHOENIX CONTACT AXL F BK PN",
            "lang": "en"
          }
        ],
        "deprecatedBy": null
      }
    }
  ],
  "opencpe": [
    {
      "name": "cpe:2.3:h:phoenixcontact:axl_f_bk_pn:-:*:*:*:*:*:*:*",
      "title": "PHOENIX CONTACT AXL F BK PN",
      "deprecated": false,
      "deprecated_over": ""
    }
  ]
}
