{
  "nist": [
    {
      "cpe": {
        "deprecated": false,
        "cpeName": "cpe:2.3:o:arm:arm-trusted-firmware:0.2:*:*:*:*:*:*:*",
        "cpeNameId": "3F9D3D9C-FC8F-4467-BF8F-A7F22AA2B803",
        "lastModified": "2019-09-24T12:42:45.197",
        "created": "2019-09-24T12:42:45.197",
        "titles": [
          {
            "title": "ARM Trusted Firmware 0.2",
            "lang": "en"
          }
        ],
        "deprecatedBy": null
      }
    },
    {
      "cpe": {
        "deprecated": false,
        "cpeName": "cpe:2.3:o:arm:arm-trusted-firmware:0.3:*:*:*:*:*:*:*",
        "cpeNameId": "3152C4B6-3B72-49DF-BF97-11A1B7775501",
        "lastModified": "2019-09-24T12:42:45.430",
        "created": "2019-09-24T12:42:45.430",
        "titles": [
          {
            "title": "ARM Trusted Firmware 0.3",
            "lang": "en"
          }
        ],
        "deprecatedBy": null
      }
    },
    {
      "cpe": {
        "deprecated": false,
        "cpeName": "cpe:2.3:o:arm:arm-trusted-firmware:0.4:-:*:*:*:*:*:*",
        "cpeNameId": "C2067901-6196-4189-AB47-77B78DFDAC8F",
        "lastModified": "2019-09-24T12:42:45.573",
        "created": "2019-09-24T12:42:45.573",
        "titles": [
          {
            "title": "ARM Trusted Firmware 0.4",
            "lang": "en"
          }
        ],
        "deprecatedBy": null
      }
    },
    {
      "cpe": {
        "deprecated": false,
        "cpeName": "cpe:2.3:o:arm:arm-trusted-firmware:0.4:rc0:*:*:*:*:*:*",
        "cpeNameId": "3F09D298-A734-4C8C-B154-CAB8F17E1F59",
        "lastModified": "2019-09-24T12:42:45.697",
        "created": "2019-09-24T12:42:45.697",
        "titles": [
          {
            "title": "ARM Trusted Firmware 0.4 Release Candidate 0",
            "lang": "en"
          }
        ],
        "deprecatedBy": null
      }
    },
    {
      "cpe": {
        "deprecated": false,
        "cpeName": "cpe:2.3:o:arm:arm-trusted-firmware:0.4:rc1:*:*:*:*:*:*",
        "cpeNameId": "7B44254D-CF2A-4614-B953-E50DE4570605",
        "lastModified": "2019-09-24T12:42:45.837",
        "created": "2019-09-24T12:42:45.837",
        "titles": [
          {
            "title": "ARM Trusted Firmware 0.4 Release Candidate 1",
            "lang": "en"
          }
        ],
        "deprecatedBy": null
      }
    },
    {
      "cpe": {
        "deprecated": false,
        "cpeName": "cpe:2.3:o:arm:arm-trusted-firmware:0.4:rc2:*:*:*:*:*:*",
        "cpeNameId": "83C060D7-4F1A-4A33-BB55-925A79F05F6C",
        "lastModified": "2019-09-24T12:42:45.977",
        "created": "2019-09-24T12:42:45.977",
        "titles": [
          {
            "title": "ARM Trusted Firmware 0.4 Release Candidate 2",
            "lang": "en"
          }
        ],
        "deprecatedBy": null
      }
    },
    {
      "cpe": {
        "deprecated": false,
        "cpeName": "cpe:2.3:o:arm:arm-trusted-firmware:0.5:-:*:*:*:*:*:*",
        "cpeNameId": "C825CE11-7F0E-4D3B-9658-30E2930F20B9",
        "lastModified": "2019-09-24T12:42:46.120",
        "created": "2019-09-24T12:42:46.120",
        "titles": [
          {
            "title": "ARM Trusted Firmware 0.5",
            "lang": "en"
          }
        ],
        "deprecatedBy": null
      }
    },
    {
      "cpe": {
        "deprecated": false,
        "cpeName": "cpe:2.3:o:arm:arm-trusted-firmware:0.5:rc0:*:*:*:*:*:*",
        "cpeNameId": "B6BAB539-CC6A-43DF-8B93-2B5CD82A2C95",
        "lastModified": "2019-09-24T12:42:46.260",
        "created": "2019-09-24T12:42:46.260",
        "titles": [
          {
            "title": "ARM Trusted Firmware 0.5 Release Candidate 0",
            "lang": "en"
          }
        ],
        "deprecatedBy": null
      }
    },
    {
      "cpe": {
        "deprecated": false,
        "cpeName": "cpe:2.3:o:arm:arm-trusted-firmware:0.5:rc1:*:*:*:*:*:*",
        "cpeNameId": "45B47C64-A774-440E-BCC7-13BD9FD6582B",
        "lastModified": "2019-09-24T12:42:46.400",
        "created": "2019-09-24T12:42:46.400",
        "titles": [
          {
            "title": "ARM Trusted Firmware 0.5 Release Candidate 1",
            "lang": "en"
          }
        ],
        "deprecatedBy": null
      }
    },
    {
      "cpe": {
        "deprecated": false,
        "cpeName": "cpe:2.3:o:arm:arm-trusted-firmware:0.6:rc0:*:*:*:*:*:*",
        "cpeNameId": "0E170DFF-9855-44D2-8F6F-E58829E41124",
        "lastModified": "2019-09-24T12:42:46.540",
        "created": "2019-09-24T12:42:46.540",
        "titles": [
          {
            "title": "ARM Trusted Firmware 0.6 Release Candidate 0",
            "lang": "en"
          }
        ],
        "deprecatedBy": null
      }
    },
    {
      "cpe": {
        "deprecated": false,
        "cpeName": "cpe:2.3:o:arm:arm-trusted-firmware:0.6:rc1:*:*:*:*:*:*",
        "cpeNameId": "3ADCD2FF-0D00-42E0-8F5D-1C3C7A39F8ED",
        "lastModified": "2019-09-24T12:42:46.697",
        "created": "2019-09-24T12:42:46.697",
        "titles": [
          {
            "title": "ARM Trusted Firmware 0.6 Release Candidate 1",
            "lang": "en"
          }
        ],
        "deprecatedBy": null
      }
    },
    {
      "cpe": {
        "deprecated": false,
        "cpeName": "cpe:2.3:o:arm:arm-trusted-firmware:1.0:-:*:*:*:*:*:*",
        "cpeNameId": "79F73A00-CF91-4873-97D1-7A661165D609",
        "lastModified": "2019-09-24T12:42:46.837",
        "created": "2019-09-24T12:42:46.837",
        "titles": [
          {
            "title": "ARM Trusted Firmware 1.0",
            "lang": "en"
          }
        ],
        "deprecatedBy": null
      }
    },
    {
      "cpe": {
        "deprecated": false,
        "cpeName": "cpe:2.3:o:arm:arm-trusted-firmware:1.0:rc0:*:*:*:*:*:*",
        "cpeNameId": "F71D46ED-3D50-4259-AC1D-37D5DCC9191D",
        "lastModified": "2019-09-24T12:42:46.993",
        "created": "2019-09-24T12:42:46.993",
        "titles": [
          {
            "title": "ARM Trusted Firmware 1.0 Release Candidate 0",
            "lang": "en"
          }
        ],
        "deprecatedBy": null
      }
    },
    {
      "cpe": {
        "deprecated": false,
        "cpeName": "cpe:2.3:o:arm:arm-trusted-firmware:1.1:-:*:*:*:*:*:*",
        "cpeNameId": "5F015CD8-5A7B-408D-B1CC-5FE443EAB936",
        "lastModified": "2019-09-24T12:42:47.150",
        "created": "2019-09-24T12:42:47.150",
        "titles": [
          {
            "title": "ARM Trusted Firmware 1.1",
            "lang": "en"
          }
        ],
        "deprecatedBy": null
      }
    },
    {
      "cpe": {
        "deprecated": false,
        "cpeName": "cpe:2.3:o:arm:arm-trusted-firmware:1.1:rc0:*:*:*:*:*:*",
        "cpeNameId": "96F02FE6-F2D1-46AE-97DD-EB3E3D4A6785",
        "lastModified": "2019-09-24T12:42:47.307",
        "created": "2019-09-24T12:42:47.307",
        "titles": [
          {
            "title": "ARM Trusted Firmware 1.1 Release Candidate 0",
            "lang": "en"
          }
        ],
        "deprecatedBy": null
      }
    },
    {
      "cpe": {
        "deprecated": false,
        "cpeName": "cpe:2.3:o:arm:arm-trusted-firmware:1.1:rc1:*:*:*:*:*:*",
        "cpeNameId": "2E2A87CE-A2A5-4E54-A33E-35F2D34051C2",
        "lastModified": "2019-09-24T12:42:47.463",
        "created": "2019-09-24T12:42:47.463",
        "titles": [
          {
            "title": "ARM Trusted Firmware 1.1 Release Candidate 1",
            "lang": "en"
          }
        ],
        "deprecatedBy": null
      }
    },
    {
      "cpe": {
        "deprecated": false,
        "cpeName": "cpe:2.3:o:arm:arm-trusted-firmware:1.1:rc2:*:*:*:*:*:*",
        "cpeNameId": "693BE394-FFCC-4999-BA57-2023C941E23C",
        "lastModified": "2019-09-24T12:42:47.620",
        "created": "2019-09-24T12:42:47.620",
        "titles": [
          {
            "title": "ARM Trusted Firmware 1.1 Release Candidate 2",
            "lang": "en"
          }
        ],
        "deprecatedBy": null
      }
    },
    {
      "cpe": {
        "deprecated": false,
        "cpeName": "cpe:2.3:o:arm:arm-trusted-firmware:1.1:rc3:*:*:*:*:*:*",
        "cpeNameId": "55DEC7BA-726D-4484-8842-2DE8B9620C57",
        "lastModified": "2019-09-24T12:42:47.790",
        "created": "2019-09-24T12:42:47.790",
        "titles": [
          {
            "title": "ARM Trusted Firmware 1.1 Release Candidate 3",
            "lang": "en"
          }
        ],
        "deprecatedBy": null
      }
    },
    {
      "cpe": {
        "deprecated": false,
        "cpeName": "cpe:2.3:o:arm:arm-trusted-firmware:1.2:-:*:*:*:*:*:*",
        "cpeNameId": "A37FEF1F-9BA4-4E53-A2D9-85A2658F41CF",
        "lastModified": "2019-09-24T12:42:47.977",
        "created": "2019-09-24T12:42:47.977",
        "titles": [
          {
            "title": "ARM Trusted Firmware 1.2",
            "lang": "en"
          }
        ],
        "deprecatedBy": null
      }
    },
    {
      "cpe": {
        "deprecated": false,
        "cpeName": "cpe:2.3:o:arm:arm-trusted-firmware:1.2:rc0:*:*:*:*:*:*",
        "cpeNameId": "FE48235D-035A-484F-99F3-5EAAF70194DF",
        "lastModified": "2019-09-24T12:42:48.150",
        "created": "2019-09-24T12:42:48.150",
        "titles": [
          {
            "title": "ARM Trusted Firmware 1.2 Release Candidate 0",
            "lang": "en"
          }
        ],
        "deprecatedBy": null
      }
    },
    {
      "cpe": {
        "deprecated": false,
        "cpeName": "cpe:2.3:o:arm:arm-trusted-firmware:1.3:-:*:*:*:*:*:*",
        "cpeNameId": "4EEB9B8B-E43B-4EDF-8559-F9531A625DB5",
        "lastModified": "2019-09-24T12:42:48.323",
        "created": "2019-09-24T12:42:48.323",
        "titles": [
          {
            "title": "ARM Trusted Firmware 1.3",
            "lang": "en"
          }
        ],
        "deprecatedBy": null
      }
    },
    {
      "cpe": {
        "deprecated": false,
        "cpeName": "cpe:2.3:o:arm:arm-trusted-firmware:1.3:rc0:*:*:*:*:*:*",
        "cpeNameId": "70302665-C256-4784-93B1-6B3F57B9FC4B",
        "lastModified": "2019-09-24T12:42:48.510",
        "created": "2019-09-24T12:42:48.510",
        "titles": [
          {
            "title": "ARM Trusted Firmware 1.3 Release Candidate 0",
            "lang": "en"
          }
        ],
        "deprecatedBy": null
      }
    },
    {
      "cpe": {
        "deprecated": false,
        "cpeName": "cpe:2.3:o:arm:arm-trusted-firmware:1.3:rc1:*:*:*:*:*:*",
        "cpeNameId": "935DA859-AA20-4A25-961E-EB54B95CFB12",
        "lastModified": "2019-09-24T12:42:48.667",
        "created": "2019-09-24T12:42:48.667",
        "titles": [
          {
            "title": "ARM Trusted Firmware 1.3 Release Candidate 1",
            "lang": "en"
          }
        ],
        "deprecatedBy": null
      }
    },
    {
      "cpe": {
        "deprecated": false,
        "cpeName": "cpe:2.3:o:arm:arm-trusted-firmware:1.3:rc2:*:*:*:*:*:*",
        "cpeNameId": "E18B20AC-F3AF-4143-9B1F-FF130198B6CB",
        "lastModified": "2019-09-24T12:42:48.837",
        "created": "2019-09-24T12:42:48.837",
        "titles": [
          {
            "title": "ARM Trusted Firmware 1.3 Release Candidate 2",
            "lang": "en"
          }
        ],
        "deprecatedBy": null
      }
    },
    {
      "cpe": {
        "deprecated": false,
        "cpeName": "cpe:2.3:o:arm:arm-trusted-firmware:1.4:-:*:*:*:*:*:*",
        "cpeNameId": "BC34963F-C819-437E-8FF9-063AFE392519",
        "lastModified": "2019-09-24T12:42:49.010",
        "created": "2019-09-24T12:42:49.010",
        "titles": [
          {
            "title": "ARM Trusted Firmware 1.4",
            "lang": "en"
          }
        ],
        "deprecatedBy": null
      }
    },
    {
      "cpe": {
        "deprecated": false,
        "cpeName": "cpe:2.3:o:arm:arm-trusted-firmware:1.4:rc0:*:*:*:*:*:*",
        "cpeNameId": "033465FE-86E5-45B8-A5DA-168E1C0411D6",
        "lastModified": "2019-09-24T12:42:49.183",
        "created": "2019-09-24T12:42:49.183",
        "titles": [
          {
            "title": "ARM Trusted Firmware 1.4 Release Candidate 0",
            "lang": "en"
          }
        ],
        "deprecatedBy": null
      }
    },
    {
      "cpe": {
        "deprecated": false,
        "cpeName": "cpe:2.3:o:arm:arm-trusted-firmware:1.5:-:*:*:*:*:*:*",
        "cpeNameId": "964E65DF-95B0-4B0C-BAF4-7DE4410AD78D",
        "lastModified": "2019-09-24T12:42:49.337",
        "created": "2019-09-24T12:42:49.337",
        "titles": [
          {
            "title": "ARM Trusted Firmware 1.5",
            "lang": "en"
          }
        ],
        "deprecatedBy": null
      }
    },
    {
      "cpe": {
        "deprecated": false,
        "cpeName": "cpe:2.3:o:arm:arm-trusted-firmware:1.5:rc0:*:*:*:*:*:*",
        "cpeNameId": "1CB52D61-B94B-4601-80AD-30E3835E7C9C",
        "lastModified": "2019-09-24T12:42:49.493",
        "created": "2019-09-24T12:42:49.493",
        "titles": [
          {
            "title": "ARM Trusted Firmware 1.5 Release Candidate 0",
            "lang": "en"
          }
        ],
        "deprecatedBy": null
      }
    },
    {
      "cpe": {
        "deprecated": false,
        "cpeName": "cpe:2.3:o:arm:arm-trusted-firmware:1.5:rc1:*:*:*:*:*:*",
        "cpeNameId": "7F549442-7807-4809-AA86-ECB807A19C46",
        "lastModified": "2019-09-24T12:42:49.667",
        "created": "2019-09-24T12:42:49.667",
        "titles": [
          {
            "title": "ARM Trusted Firmware 1.5 Release Candidate 1",
            "lang": "en"
          }
        ],
        "deprecatedBy": null
      }
    },
    {
      "cpe": {
        "deprecated": false,
        "cpeName": "cpe:2.3:o:arm:arm-trusted-firmware:1.5:rc2:*:*:*:*:*:*",
        "cpeNameId": "03E3DF38-DA5D-48B3-8728-0AAB98C61E4B",
        "lastModified": "2019-09-24T12:42:49.837",
        "created": "2019-09-24T12:42:49.837",
        "titles": [
          {
            "title": "ARM Trusted Firmware 1.5 Release Candidate 2",
            "lang": "en"
          }
        ],
        "deprecatedBy": null
      }
    },
    {
      "cpe": {
        "deprecated": false,
        "cpeName": "cpe:2.3:o:arm:arm-trusted-firmware:1.5:rc3:*:*:*:*:*:*",
        "cpeNameId": "DEF15767-A888-4BAB-A905-27318E880DE4",
        "lastModified": "2019-09-24T12:42:50.010",
        "created": "2019-09-24T12:42:50.010",
        "titles": [
          {
            "title": "ARM Trusted Firmware 1.5 Release Candidate 3",
            "lang": "en"
          }
        ],
        "deprecatedBy": null
      }
    },
    {
      "cpe": {
        "deprecated": false,
        "cpeName": "cpe:2.3:o:arm:arm-trusted-firmware:1.6:-:*:*:*:*:*:*",
        "cpeNameId": "0C8F27D9-824E-404A-A2EB-4660E8C96F87",
        "lastModified": "2019-09-24T12:42:50.183",
        "created": "2019-09-24T12:42:50.183",
        "titles": [
          {
            "title": "ARM Trusted Firmware 1.6",
            "lang": "en"
          }
        ],
        "deprecatedBy": null
      }
    },
    {
      "cpe": {
        "deprecated": false,
        "cpeName": "cpe:2.3:o:arm:arm-trusted-firmware:1.6:rc0:*:*:*:*:*:*",
        "cpeNameId": "E6AD3912-8E17-4AD6-85CE-FFBDFC8412FE",
        "lastModified": "2019-09-24T12:42:50.353",
        "created": "2019-09-24T12:42:50.353",
        "titles": [
          {
            "title": "ARM Trusted Firmware 1.6 Release Candidate 0",
            "lang": "en"
          }
        ],
        "deprecatedBy": null
      }
    },
    {
      "cpe": {
        "deprecated": false,
        "cpeName": "cpe:2.3:o:arm:arm-trusted-firmware:1.6:rc1:*:*:*:*:*:*",
        "cpeNameId": "2B2FC3E5-95FF-4A54-B781-09FF36DB6A7B",
        "lastModified": "2019-09-24T12:42:50.540",
        "created": "2019-09-24T12:42:50.540",
        "titles": [
          {
            "title": "ARM Trusted Firmware 1.6 Release Candidate 1",
            "lang": "en"
          }
        ],
        "deprecatedBy": null
      }
    },
    {
      "cpe": {
        "deprecated": false,
        "cpeName": "cpe:2.3:o:arm:arm-trusted-firmware:2.0:-:*:*:*:*:*:*",
        "cpeNameId": "10040F80-B860-423C-8565-ADF767C02153",
        "lastModified": "2019-09-24T12:42:50.713",
        "created": "2019-09-24T12:42:50.713",
        "titles": [
          {
            "title": "ARM Trusted Firmware 2.0",
            "lang": "en"
          }
        ],
        "deprecatedBy": null
      }
    },
    {
      "cpe": {
        "deprecated": false,
        "cpeName": "cpe:2.3:o:arm:arm-trusted-firmware:2.0:rc0:*:*:*:*:*:*",
        "cpeNameId": "1ED5F97A-A36D-40BE-B09F-B65CAD6733D9",
        "lastModified": "2019-09-24T12:42:50.900",
        "created": "2019-09-24T12:42:50.900",
        "titles": [
          {
            "title": "ARM Trusted Firmware 2.0 Release Candidate 0",
            "lang": "en"
          }
        ],
        "deprecatedBy": null
      }
    },
    {
      "cpe": {
        "deprecated": false,
        "cpeName": "cpe:2.3:o:arm:arm-trusted-firmware:2.1:-:*:*:*:*:*:*",
        "cpeNameId": "DECDD28F-BEBA-462B-847C-E8789526A9F3",
        "lastModified": "2019-09-24T12:42:51.087",
        "created": "2019-09-24T12:42:51.087",
        "titles": [
          {
            "title": "ARM Trusted Firmware 2.1",
            "lang": "en"
          }
        ],
        "deprecatedBy": null
      }
    },
    {
      "cpe": {
        "deprecated": false,
        "cpeName": "cpe:2.3:o:arm:arm-trusted-firmware:2.1:rc0:*:*:*:*:*:*",
        "cpeNameId": "43445D3A-2DF4-4D5B-8619-81038FE1633E",
        "lastModified": "2019-09-24T12:42:51.277",
        "created": "2019-09-24T12:42:51.277",
        "titles": [
          {
            "title": "ARM Trusted Firmware 2.1 Release Candidate 0",
            "lang": "en"
          }
        ],
        "deprecatedBy": null
      }
    },
    {
      "cpe": {
        "deprecated": false,
        "cpeName": "cpe:2.3:o:arm:arm-trusted-firmware:2.1:rc1:*:*:*:*:*:*",
        "cpeNameId": "3E958C58-B964-4DCE-A662-C180DB2D3CD5",
        "lastModified": "2019-09-24T12:42:51.463",
        "created": "2019-09-24T12:42:51.463",
        "titles": [
          {
            "title": "ARM Trusted Firmware 2.1 Release Candidate 1",
            "lang": "en"
          }
        ],
        "deprecatedBy": null
      }
    },
    {
      "cpe": {
        "deprecated": false,
        "cpeName": "cpe:2.3:o:arm:arm-trusted-firmware:2.4:-:*:*:*:*:*:*",
        "cpeNameId": "78601535-610A-45A5-A5F0-AFC6A27A7F83",
        "lastModified": "2021-03-23T17:05:30.197",
        "created": "2021-03-12T15:09:01.913",
        "titles": [
          {
            "title": "ARM Trusted Firmware 2.4",
            "lang": "en"
          }
        ],
        "deprecatedBy": null
      }
    },
    {
      "cpe": {
        "deprecated": false,
        "cpeName": "cpe:2.3:o:arm:arm-trusted-firmware:2.3:-:*:*:*:*:*:*",
        "cpeNameId": "AC2E54B8-9B7C-4A6D-806B-6842FCE5AB2E",
        "lastModified": "2021-03-23T17:05:30.197",
        "created": "2021-03-12T15:09:01.913",
        "titles": [
          {
            "title": "ARM Trusted Firmware 2.3",
            "lang": "en"
          }
        ],
        "deprecatedBy": null
      }
    },
    {
      "cpe": {
        "deprecated": false,
        "cpeName": "cpe:2.3:o:arm:arm-trusted-firmware:2.2:-:*:*:*:*:*:*",
        "cpeNameId": "208C5E96-AE3A-44B2-ACA6-D5C14D7441AA",
        "lastModified": "2021-03-23T17:05:30.197",
        "created": "2021-03-12T15:09:01.913",
        "titles": [
          {
            "title": "ARM Trusted Firmware 2.2",
            "lang": "en"
          }
        ],
        "deprecatedBy": null
      }
    },
    {
      "cpe": {
        "deprecated": false,
        "cpeName": "cpe:2.3:o:arm:arm-trusted-firmware:2.4:rc0:*:*:*:*:*:*",
        "cpeNameId": "36D31B42-67CA-4C53-98C3-458A394D8F82",
        "lastModified": "2021-03-23T17:05:30.197",
        "created": "2021-03-12T15:09:35.993",
        "titles": [
          {
            "title": "ARM Trusted Firmware 2.4 Release Candidate 0",
            "lang": "en"
          }
        ],
        "deprecatedBy": null
      }
    },
    {
      "cpe": {
        "deprecated": false,
        "cpeName": "cpe:2.3:o:arm:arm-trusted-firmware:2.4:rc1:*:*:*:*:*:*",
        "cpeNameId": "9356CF5F-980E-4A53-BE38-ACCFE4302680",
        "lastModified": "2021-03-23T17:05:30.197",
        "created": "2021-03-12T15:09:35.993",
        "titles": [
          {
            "title": "ARM Trusted Firmware 2.4 Release Candidate 1",
            "lang": "en"
          }
        ],
        "deprecatedBy": null
      }
    },
    {
      "cpe": {
        "deprecated": false,
        "cpeName": "cpe:2.3:o:arm:arm-trusted-firmware:2.4:rc2:*:*:*:*:*:*",
        "cpeNameId": "6348F0DA-F04B-4CD7-B063-335704DF7C54",
        "lastModified": "2021-03-23T17:05:30.197",
        "created": "2021-03-12T15:09:35.993",
        "titles": [
          {
            "title": "ARM Trusted Firmware 2.4 Release Candidate 2",
            "lang": "en"
          }
        ],
        "deprecatedBy": null
      }
    },
    {
      "cpe": {
        "deprecated": false,
        "cpeName": "cpe:2.3:o:arm:arm-trusted-firmware:2.3:rc0:*:*:*:*:*:*",
        "cpeNameId": "29A573E6-17B8-4A3F-B494-46DEEC86772C",
        "lastModified": "2021-03-23T17:05:30.197",
        "created": "2021-03-12T15:11:02.917",
        "titles": [
          {
            "title": "ARM Trusted Firmware 2.3 Release Candidate 0",
            "lang": "en"
          }
        ],
        "deprecatedBy": null
      }
    },
    {
      "cpe": {
        "deprecated": false,
        "cpeName": "cpe:2.3:o:arm:arm-trusted-firmware:2.3:rc1:*:*:*:*:*:*",
        "cpeNameId": "85930A9D-23C3-4898-A2FF-E858B9B30C03",
        "lastModified": "2021-03-23T17:05:30.197",
        "created": "2021-03-12T15:11:02.917",
        "titles": [
          {
            "title": "ARM Trusted Firmware 2.3 Release Candidate 1",
            "lang": "en"
          }
        ],
        "deprecatedBy": null
      }
    },
    {
      "cpe": {
        "deprecated": false,
        "cpeName": "cpe:2.3:o:arm:arm-trusted-firmware:2.3:rc2:*:*:*:*:*:*",
        "cpeNameId": "F05CE8EC-C2D3-45FE-B0B4-85C11D47DB2B",
        "lastModified": "2021-03-23T17:05:30.197",
        "created": "2021-03-12T15:11:02.917",
        "titles": [
          {
            "title": "ARM Trusted Firmware 2.3 Release Candidate 2",
            "lang": "en"
          }
        ],
        "deprecatedBy": null
      }
    },
    {
      "cpe": {
        "deprecated": false,
        "cpeName": "cpe:2.3:o:arm:arm-trusted-firmware:2.2:rc0:*:*:*:*:*:*",
        "cpeNameId": "582F8473-00B1-4911-9FAC-0DDC37E0B948",
        "lastModified": "2021-03-23T17:05:30.197",
        "created": "2021-03-12T15:24:51.390",
        "titles": [
          {
            "title": "ARM Trusted Firmware 2.2 Release Candidate 0",
            "lang": "en"
          }
        ],
        "deprecatedBy": null
      }
    },
    {
      "cpe": {
        "deprecated": false,
        "cpeName": "cpe:2.3:o:arm:arm-trusted-firmware:2.2:rc1:*:*:*:*:*:*",
        "cpeNameId": "D2C2537D-1300-4E38-BD4E-DE0BD6C3062D",
        "lastModified": "2021-03-23T17:05:30.197",
        "created": "2021-03-12T15:24:51.390",
        "titles": [
          {
            "title": "ARM Trusted Firmware 2.2 Release Candidate 1",
            "lang": "en"
          }
        ],
        "deprecatedBy": null
      }
    },
    {
      "cpe": {
        "deprecated": false,
        "cpeName": "cpe:2.3:o:arm:arm-trusted-firmware:2.2:rc2:*:*:*:*:*:*",
        "cpeNameId": "7E9EE3F8-C662-4A15-91FA-343B077471DC",
        "lastModified": "2021-03-23T17:05:30.197",
        "created": "2021-03-12T15:24:51.390",
        "titles": [
          {
            "title": "ARM Trusted Firmware 2.2 Release Candidate 2",
            "lang": "en"
          }
        ],
        "deprecatedBy": null
      }
    }
  ],
  "opencpe": [
    {
      "name": "cpe:2.3:o:arm:arm-trusted-firmware:0.2:*:*:*:*:*:*:*",
      "title": "ARM Trusted Firmware 0.2",
      "deprecated": false,
      "deprecated_over": ""
    },
    {
      "name": "cpe:2.3:o:arm:arm-trusted-firmware:0.3:*:*:*:*:*:*:*",
      "title": "ARM Trusted Firmware 0.3",
      "deprecated": false,
      "deprecated_over": ""
    },
    {
      "name": "cpe:2.3:o:arm:arm-trusted-firmware:0.4:-:*:*:*:*:*:*",
      "title": "ARM Trusted Firmware 0.4",
      "deprecated": false,
      "deprecated_over": ""
    },
    {
      "name": "cpe:2.3:o:arm:arm-trusted-firmware:0.4:rc0:*:*:*:*:*:*",
      "title": "ARM Trusted Firmware 0.4 Release Candidate 0",
      "deprecated": false,
      "deprecated_over": ""
    },
    {
      "name": "cpe:2.3:o:arm:arm-trusted-firmware:0.4:rc1:*:*:*:*:*:*",
      "title": "ARM Trusted Firmware 0.4 Release Candidate 1",
      "deprecated": false,
      "deprecated_over": ""
    },
    {
      "name": "cpe:2.3:o:arm:arm-trusted-firmware:0.4:rc2:*:*:*:*:*:*",
      "title": "ARM Trusted Firmware 0.4 Release Candidate 2",
      "deprecated": false,
      "deprecated_over": ""
    },
    {
      "name": "cpe:2.3:o:arm:arm-trusted-firmware:0.5:-:*:*:*:*:*:*",
      "title": "ARM Trusted Firmware 0.5",
      "deprecated": false,
      "deprecated_over": ""
    },
    {
      "name": "cpe:2.3:o:arm:arm-trusted-firmware:0.5:rc0:*:*:*:*:*:*",
      "title": "ARM Trusted Firmware 0.5 Release Candidate 0",
      "deprecated": false,
      "deprecated_over": ""
    },
    {
      "name": "cpe:2.3:o:arm:arm-trusted-firmware:0.5:rc1:*:*:*:*:*:*",
      "title": "ARM Trusted Firmware 0.5 Release Candidate 1",
      "deprecated": false,
      "deprecated_over": ""
    },
    {
      "name": "cpe:2.3:o:arm:arm-trusted-firmware:0.6:rc0:*:*:*:*:*:*",
      "title": "ARM Trusted Firmware 0.6 Release Candidate 0",
      "deprecated": false,
      "deprecated_over": ""
    },
    {
      "name": "cpe:2.3:o:arm:arm-trusted-firmware:0.6:rc1:*:*:*:*:*:*",
      "title": "ARM Trusted Firmware 0.6 Release Candidate 1",
      "deprecated": false,
      "deprecated_over": ""
    },
    {
      "name": "cpe:2.3:o:arm:arm-trusted-firmware:1.0:-:*:*:*:*:*:*",
      "title": "ARM Trusted Firmware 1.0",
      "deprecated": false,
      "deprecated_over": ""
    },
    {
      "name": "cpe:2.3:o:arm:arm-trusted-firmware:1.0:rc0:*:*:*:*:*:*",
      "title": "ARM Trusted Firmware 1.0 Release Candidate 0",
      "deprecated": false,
      "deprecated_over": ""
    },
    {
      "name": "cpe:2.3:o:arm:arm-trusted-firmware:1.1:-:*:*:*:*:*:*",
      "title": "ARM Trusted Firmware 1.1",
      "deprecated": false,
      "deprecated_over": ""
    },
    {
      "name": "cpe:2.3:o:arm:arm-trusted-firmware:1.1:rc0:*:*:*:*:*:*",
      "title": "ARM Trusted Firmware 1.1 Release Candidate 0",
      "deprecated": false,
      "deprecated_over": ""
    },
    {
      "name": "cpe:2.3:o:arm:arm-trusted-firmware:1.1:rc1:*:*:*:*:*:*",
      "title": "ARM Trusted Firmware 1.1 Release Candidate 1",
      "deprecated": false,
      "deprecated_over": ""
    },
    {
      "name": "cpe:2.3:o:arm:arm-trusted-firmware:1.1:rc2:*:*:*:*:*:*",
      "title": "ARM Trusted Firmware 1.1 Release Candidate 2",
      "deprecated": false,
      "deprecated_over": ""
    },
    {
      "name": "cpe:2.3:o:arm:arm-trusted-firmware:1.1:rc3:*:*:*:*:*:*",
      "title": "ARM Trusted Firmware 1.1 Release Candidate 3",
      "deprecated": false,
      "deprecated_over": ""
    },
    {
      "name": "cpe:2.3:o:arm:arm-trusted-firmware:1.2:-:*:*:*:*:*:*",
      "title": "ARM Trusted Firmware 1.2",
      "deprecated": false,
      "deprecated_over": ""
    },
    {
      "name": "cpe:2.3:o:arm:arm-trusted-firmware:1.2:rc0:*:*:*:*:*:*",
      "title": "ARM Trusted Firmware 1.2 Release Candidate 0",
      "deprecated": false,
      "deprecated_over": ""
    },
    {
      "name": "cpe:2.3:o:arm:arm-trusted-firmware:1.3:-:*:*:*:*:*:*",
      "title": "ARM Trusted Firmware 1.3",
      "deprecated": false,
      "deprecated_over": ""
    },
    {
      "name": "cpe:2.3:o:arm:arm-trusted-firmware:1.3:rc0:*:*:*:*:*:*",
      "title": "ARM Trusted Firmware 1.3 Release Candidate 0",
      "deprecated": false,
      "deprecated_over": ""
    },
    {
      "name": "cpe:2.3:o:arm:arm-trusted-firmware:1.3:rc1:*:*:*:*:*:*",
      "title": "ARM Trusted Firmware 1.3 Release Candidate 1",
      "deprecated": false,
      "deprecated_over": ""
    },
    {
      "name": "cpe:2.3:o:arm:arm-trusted-firmware:1.3:rc2:*:*:*:*:*:*",
      "title": "ARM Trusted Firmware 1.3 Release Candidate 2",
      "deprecated": false,
      "deprecated_over": ""
    },
    {
      "name": "cpe:2.3:o:arm:arm-trusted-firmware:1.4:-:*:*:*:*:*:*",
      "title": "ARM Trusted Firmware 1.4",
      "deprecated": false,
      "deprecated_over": ""
    },
    {
      "name": "cpe:2.3:o:arm:arm-trusted-firmware:1.4:rc0:*:*:*:*:*:*",
      "title": "ARM Trusted Firmware 1.4 Release Candidate 0",
      "deprecated": false,
      "deprecated_over": ""
    },
    {
      "name": "cpe:2.3:o:arm:arm-trusted-firmware:1.5:-:*:*:*:*:*:*",
      "title": "ARM Trusted Firmware 1.5",
      "deprecated": false,
      "deprecated_over": ""
    },
    {
      "name": "cpe:2.3:o:arm:arm-trusted-firmware:1.5:rc0:*:*:*:*:*:*",
      "title": "ARM Trusted Firmware 1.5 Release Candidate 0",
      "deprecated": false,
      "deprecated_over": ""
    },
    {
      "name": "cpe:2.3:o:arm:arm-trusted-firmware:1.5:rc1:*:*:*:*:*:*",
      "title": "ARM Trusted Firmware 1.5 Release Candidate 1",
      "deprecated": false,
      "deprecated_over": ""
    },
    {
      "name": "cpe:2.3:o:arm:arm-trusted-firmware:1.5:rc2:*:*:*:*:*:*",
      "title": "ARM Trusted Firmware 1.5 Release Candidate 2",
      "deprecated": false,
      "deprecated_over": ""
    },
    {
      "name": "cpe:2.3:o:arm:arm-trusted-firmware:1.5:rc3:*:*:*:*:*:*",
      "title": "ARM Trusted Firmware 1.5 Release Candidate 3",
      "deprecated": false,
      "deprecated_over": ""
    },
    {
      "name": "cpe:2.3:o:arm:arm-trusted-firmware:1.6:-:*:*:*:*:*:*",
      "title": "ARM Trusted Firmware 1.6",
      "deprecated": false,
      "deprecated_over": ""
    },
    {
      "name": "cpe:2.3:o:arm:arm-trusted-firmware:1.6:rc0:*:*:*:*:*:*",
      "title": "ARM Trusted Firmware 1.6 Release Candidate 0",
      "deprecated": false,
      "deprecated_over": ""
    },
    {
      "name": "cpe:2.3:o:arm:arm-trusted-firmware:1.6:rc1:*:*:*:*:*:*",
      "title": "ARM Trusted Firmware 1.6 Release Candidate 1",
      "deprecated": false,
      "deprecated_over": ""
    },
    {
      "name": "cpe:2.3:o:arm:arm-trusted-firmware:2.0:-:*:*:*:*:*:*",
      "title": "ARM Trusted Firmware 2.0",
      "deprecated": false,
      "deprecated_over": ""
    },
    {
      "name": "cpe:2.3:o:arm:arm-trusted-firmware:2.0:rc0:*:*:*:*:*:*",
      "title": "ARM Trusted Firmware 2.0 Release Candidate 0",
      "deprecated": false,
      "deprecated_over": ""
    },
    {
      "name": "cpe:2.3:o:arm:arm-trusted-firmware:2.1:-:*:*:*:*:*:*",
      "title": "ARM Trusted Firmware 2.1",
      "deprecated": false,
      "deprecated_over": ""
    },
    {
      "name": "cpe:2.3:o:arm:arm-trusted-firmware:2.1:rc0:*:*:*:*:*:*",
      "title": "ARM Trusted Firmware 2.1 Release Candidate 0",
      "deprecated": false,
      "deprecated_over": ""
    },
    {
      "name": "cpe:2.3:o:arm:arm-trusted-firmware:2.1:rc1:*:*:*:*:*:*",
      "title": "ARM Trusted Firmware 2.1 Release Candidate 1",
      "deprecated": false,
      "deprecated_over": ""
    },
    {
      "name": "cpe:2.3:o:arm:arm-trusted-firmware:2.4:-:*:*:*:*:*:*",
      "title": "ARM Trusted Firmware 2.4",
      "deprecated": false,
      "deprecated_over": ""
    },
    {
      "name": "cpe:2.3:o:arm:arm-trusted-firmware:2.3:-:*:*:*:*:*:*",
      "title": "ARM Trusted Firmware 2.3",
      "deprecated": false,
      "deprecated_over": ""
    },
    {
      "name": "cpe:2.3:o:arm:arm-trusted-firmware:2.2:-:*:*:*:*:*:*",
      "title": "ARM Trusted Firmware 2.2",
      "deprecated": false,
      "deprecated_over": ""
    },
    {
      "name": "cpe:2.3:o:arm:arm-trusted-firmware:2.4:rc0:*:*:*:*:*:*",
      "title": "ARM Trusted Firmware 2.4 Release Candidate 0",
      "deprecated": false,
      "deprecated_over": ""
    },
    {
      "name": "cpe:2.3:o:arm:arm-trusted-firmware:2.4:rc1:*:*:*:*:*:*",
      "title": "ARM Trusted Firmware 2.4 Release Candidate 1",
      "deprecated": false,
      "deprecated_over": ""
    },
    {
      "name": "cpe:2.3:o:arm:arm-trusted-firmware:2.4:rc2:*:*:*:*:*:*",
      "title": "ARM Trusted Firmware 2.4 Release Candidate 2",
      "deprecated": false,
      "deprecated_over": ""
    },
    {
      "name": "cpe:2.3:o:arm:arm-trusted-firmware:2.3:rc0:*:*:*:*:*:*",
      "title": "ARM Trusted Firmware 2.3 Release Candidate 0",
      "deprecated": false,
      "deprecated_over": ""
    },
    {
      "name": "cpe:2.3:o:arm:arm-trusted-firmware:2.3:rc1:*:*:*:*:*:*",
      "title": "ARM Trusted Firmware 2.3 Release Candidate 1",
      "deprecated": false,
      "deprecated_over": ""
    },
    {
      "name": "cpe:2.3:o:arm:arm-trusted-firmware:2.3:rc2:*:*:*:*:*:*",
      "title": "ARM Trusted Firmware 2.3 Release Candidate 2",
      "deprecated": false,
      "deprecated_over": ""
    },
    {
      "name": "cpe:2.3:o:arm:arm-trusted-firmware:2.2:rc0:*:*:*:*:*:*",
      "title": "ARM Trusted Firmware 2.2 Release Candidate 0",
      "deprecated": false,
      "deprecated_over": ""
    },
    {
      "name": "cpe:2.3:o:arm:arm-trusted-firmware:2.2:rc1:*:*:*:*:*:*",
      "title": "ARM Trusted Firmware 2.2 Release Candidate 1",
      "deprecated": false,
      "deprecated_over": ""
    },
    {
      "name": "cpe:2.3:o:arm:arm-trusted-firmware:2.2:rc2:*:*:*:*:*:*",
      "title": "ARM Trusted Firmware 2.2 Release Candidate 2",
      "deprecated": false,
      "deprecated_over": ""
    }
  ]
}
