{
  "nist": [
    {
      "cpe": {
        "deprecated": false,
        "cpeName": "cpe:2.3:h:mediatek:mt6757:-:*:*:*:*:*:*:*",
        "cpeNameId": "C95013CF-6F9B-4D3F-9459-5BF76D88CD3D",
        "lastModified": "2020-04-09T21:15:52.267",
        "created": "2020-04-09T21:15:52.267",
        "titles": [
          {
            "title": "MediaTek MT6757",
            "lang": "en"
          }
        ],
        "deprecatedBy": null
      }
    }
  ],
  "opencpe": [
    {
      "name": "cpe:2.3:h:mediatek:mt6757:-:*:*:*:*:*:*:*",
      "title": "MediaTek MT6757",
      "deprecated": false,
      "deprecated_over": ""
    }
  ]
}
