{
  "nist": [
    {
      "cpe": {
        "deprecated": false,
        "cpeName": "cpe:2.3:o:draytek:vigor2865l_firmware:4.4.0:*:*:*:*:*:*:*",
        "cpeNameId": "3CC18AF7-30D4-4D2E-8E26-5A9EFD23AC96",
        "lastModified": "2022-08-31T12:51:55.053",
        "created": "2022-08-31T10:28:02.307",
        "titles": [
          {
            "title": "DrayTek Vigor2865l Firmware 4.4.0",
            "lang": "en"
          }
        ],
        "deprecatedBy": null
      }
    },
    {
      "cpe": {
        "deprecated": false,
        "cpeName": "cpe:2.3:o:draytek:vigor2865l_firmware:-:*:*:*:*:*:*:*",
        "cpeNameId": "C27BCEAB-0BF6-49AD-8B53-8B9AD0919F46",
        "lastModified": "2022-08-31T12:51:25.280",
        "created": "2022-08-31T10:28:02.307",
        "titles": [
          {
            "title": "DrayTek Vigor2865l Firmware",
            "lang": "en"
          }
        ],
        "deprecatedBy": null
      }
    }
  ],
  "opencpe": [
    {
      "name": "cpe:2.3:o:draytek:vigor2865l_firmware:4.4.0:*:*:*:*:*:*:*",
      "title": "DrayTek Vigor2865l Firmware 4.4.0",
      "deprecated": false,
      "deprecated_over": ""
    },
    {
      "name": "cpe:2.3:o:draytek:vigor2865l_firmware:-:*:*:*:*:*:*:*",
      "title": "DrayTek Vigor2865l Firmware",
      "deprecated": false,
      "deprecated_over": ""
    }
  ]
}
