{
  "nist": [
    {
      "cpe": {
        "deprecated": false,
        "cpeName": "cpe:2.3:o:hp:color_laserjet_managed_flow_e67650_3gy32a_firmware:-:*:*:*:*:*:*:*",
        "cpeNameId": "4139C22E-37BF-4FA6-8C78-8421018C745D",
        "lastModified": "2023-01-09T14:23:44.100",
        "created": "2022-12-28T10:15:51.260",
        "titles": [
          {
            "title": "HP Color Laserjet Managed Flow E67650 3gy32a Firmware -",
            "lang": "en"
          }
        ],
        "deprecatedBy": null
      }
    }
  ],
  "opencpe": [
    {
      "name": "cpe:2.3:o:hp:color_laserjet_managed_flow_e67650_3gy32a_firmware:-:*:*:*:*:*:*:*",
      "title": "HP Color Laserjet Managed Flow E67650 3gy32a Firmware -",
      "deprecated": false,
      "deprecated_over": ""
    }
  ]
}
