{
  "nist": [
    {
      "cpe": {
        "deprecated": false,
        "cpeName": "cpe:2.3:o:moxa:mgate_mb3170i-m-sc_firmware:4.2:*:*:*:*:*:*:*",
        "cpeNameId": "0348C688-E5C4-406E-B0FD-8ABDFBD9EF4B",
        "lastModified": "2022-04-25T16:59:59.707",
        "created": "2022-04-25T15:51:07.010",
        "titles": [
          {
            "title": "Moxa MGate MB3170I-M-SC Firmware 4.2",
            "lang": "en"
          }
        ],
        "deprecatedBy": null
      }
    },
    {
      "cpe": {
        "deprecated": false,
        "cpeName": "cpe:2.3:o:moxa:mgate_mb3170i-m-sc_firmware:-:*:*:*:*:*:*:*",
        "cpeNameId": "42AF8699-270A-40DE-BFF9-5E2E66B951EA",
        "lastModified": "2022-04-25T16:59:59.707",
        "created": "2022-04-25T15:51:07.010",
        "titles": [
          {
            "title": "Moxa MGate MB3170I-M-SC Firmware",
            "lang": "en"
          }
        ],
        "deprecatedBy": null
      }
    }
  ],
  "opencpe": [
    {
      "name": "cpe:2.3:o:moxa:mgate_mb3170i-m-sc_firmware:4.2:*:*:*:*:*:*:*",
      "title": "Moxa MGate MB3170I-M-SC Firmware 4.2",
      "deprecated": false,
      "deprecated_over": ""
    },
    {
      "name": "cpe:2.3:o:moxa:mgate_mb3170i-m-sc_firmware:-:*:*:*:*:*:*:*",
      "title": "Moxa MGate MB3170I-M-SC Firmware",
      "deprecated": false,
      "deprecated_over": ""
    }
  ]
}
